earlybyte.py
earlybyte_mvv-0.0.5.dist-info/LICENSE
earlybyte_mvv-0.0.5.dist-info/METADATA
earlybyte_mvv-0.0.5.dist-info/WHEEL
earlybyte_mvv-0.0.5.dist-info/entry_points.txt
earlybyte_mvv-0.0.5.dist-info/top_level.txt
earlybyte_mvv-0.0.5.dist-info/RECORD
