Metadata-Version: 2.1
Name: earlybyte-mvv
Version: 0.0.5
Summary: earlybtyte mission, vision, and value statement
Home-page: https://www.earlybyte.ch
Author: Remo Hoeppli
Author-email: remo.hoeppli@earlybyte.ch
License: MIT License
Platform: UNKNOWN
Classifier: Programming Language :: Python :: 3.7
Classifier: Operating System :: OS Independent
Requires-Python: >=3.7
License-File: LICENSE
Requires-Dist: setuptools
Requires-Dist: typer (>=0.3.2)
